push_innertune_likes.py
push_innertune_likes-1.0.1.dist-info/LICENSE
push_innertune_likes-1.0.1.dist-info/METADATA
push_innertune_likes-1.0.1.dist-info/WHEEL
push_innertune_likes-1.0.1.dist-info/entry_points.txt
push_innertune_likes-1.0.1.dist-info/top_level.txt
push_innertune_likes-1.0.1.dist-info/RECORD
