Metadata-Version: 2.1
Name: push_innertune_likes
Version: 1.0.1
Summary: A basic Python script to extract liked songs from InnerTune (via an exported backup), and push those likes to YouTube Music (via ytmusicapi).
Author-email: Nicholas Mira <nicholasmira@gmail.com>
License: GNU GENERAL PUBLIC LICENSE
Project-URL: Homepage, https://github.com/nicholasmira/Push-InnerTune-Likes
Keywords: innertune
Classifier: Programming Language :: Python :: 3
License-File: LICENSE
Requires-Dist: ytmusicapi ==1.8.*
Provides-Extra: dev
Requires-Dist: pre-commit ; extra == 'dev'
